LICENSE
MANIFEST.in
README.md
requirements-macos.txt
requirements.txt
setup.py
DeepTCR/DeepTCR.py
DeepTCR/__init__.py
DeepTCR.egg-info/PKG-INFO
DeepTCR.egg-info/SOURCES.txt
DeepTCR.egg-info/dependency_links.txt
DeepTCR.egg-info/requires.txt
DeepTCR.egg-info/top_level.txt
DeepTCR/functions/Layers.py
DeepTCR/functions/Supertype_Data_Dict.csv
DeepTCR/functions/__init__.py
DeepTCR/functions/act_fun.py
DeepTCR/functions/data_processing.py
DeepTCR/functions/plot_func.py
DeepTCR/functions/utils_s.py
DeepTCR/functions/utils_u.py
DeepTCR/phenograph/__init__.py
DeepTCR/phenograph/bruteforce_nn.py
DeepTCR/phenograph/classify.py
DeepTCR/phenograph/cluster.py
DeepTCR/phenograph/core.py
DeepTCR/phenograph/louvain/community
DeepTCR/phenograph/louvain/community.exe
DeepTCR/phenograph/louvain/convert
DeepTCR/phenograph/louvain/convert.exe
DeepTCR/phenograph/louvain/hierarchy
DeepTCR/phenograph/louvain/hierarchy.exe
DeepTCR/phenograph/louvain/linux-community
DeepTCR/phenograph/louvain/linux-convert
DeepTCR/phenograph/louvain/linux-hierarchy
DeepTCR/phenograph/louvain/louvain-readme.txt
DeepTCR/phenograph/louvain/phenograph-readme.txt