Metadata-Version: 2.4
Name: DeepTCR
Version: 2.1.29
Summary: Deep Learning Methods for Parsing T-Cell Receptor Sequencing (TCRSeq) Data
Home-page: https://github.com/sidhomj/DeepTCR
Author: John-William Sidhom
Author-email: jsidhom1@jhmi.edu
License: LICENSE
License-File: LICENSE
Requires-Dist: tensorflow-macos==2.12.0
Requires-Dist: tensorflow-metal==0.8.0
Requires-Dist: numpy==1.23.5
Requires-Dist: pandas==1.5.3
Requires-Dist: scipy==1.10.1
Requires-Dist: h5py==3.8.0
Requires-Dist: scikit-learn==1.2.2
Requires-Dist: keras==2.12.0
Requires-Dist: biopython==1.76
Requires-Dist: matplotlib==3.7.2
Requires-Dist: seaborn==0.12.2
Requires-Dist: logomaker==0.8
Requires-Dist: pillow>=10.0.0
Requires-Dist: umap-learn==0.5.5
Requires-Dist: networkx==3.1
Requires-Dist: distinctipy==1.2.1
Requires-Dist: jupyterlab>=4.4.0
Requires-Dist: notebook>=7.4.0
Requires-Dist: ipykernel>=6.29.0
Requires-Dist: ipywidgets>=8.1.0
Requires-Dist: tqdm==4.66.4
Requires-Dist: psutil>=7.0.0
Requires-Dist: numba>=0.60.0
Requires-Dist: python-louvain>=0.16
Dynamic: author
Dynamic: author-email
Dynamic: description
Dynamic: description-content-type
Dynamic: home-page
Dynamic: license
Dynamic: license-file
Dynamic: requires-dist
Dynamic: summary
